README.md
setup.cfg
setup.py
pmtutils/__init__.py
pmtutils/dbhelper.py
pmtutils/hyamler.py
pmtutils/sampler.py
pmtutils.egg-info/PKG-INFO
pmtutils.egg-info/SOURCES.txt
pmtutils.egg-info/dependency_links.txt
pmtutils.egg-info/requires.txt
pmtutils.egg-info/top_level.txt