Metadata-Version: 2.1
Name: pmtutils
Version: 0.0.1
Summary: Portable toolkit for interacting with the PyMetaTome pipeline
Home-page: https://github.com/lambertsbennett/pmtutils
Author: Bennett Lambert
Author-email: lambertb@uw.edu
License: UNKNOWN
Download-URL: https://github.com/lambertsbennett/pmtutils/archive/v_01.tar.gz
Keywords: Transcriptomics,Bioinformatics
Platform: UNKNOWN
Classifier: Programming Language :: Python :: 3
Classifier: License :: OSI Approved :: MIT License
Classifier: Operating System :: Unix
Classifier: Intended Audience :: Science/Research
Classifier: Topic :: Software Development :: Libraries :: Python Modules
Classifier: Development Status :: 2 - Pre-Alpha
Requires-Python: >=3.6
